MANIFEST.in
Makefile
README.rst
requirements-tests.txt
requirements.txt
setup.py
Moar.egg-info/PKG-INFO
Moar.egg-info/SOURCES.txt
Moar.egg-info/dependency_links.txt
Moar.egg-info/not-zip-safe
Moar.egg-info/requires.txt
Moar.egg-info/top_level.txt
moar/__init__.py
moar/_compat.py
moar/optimage.py
moar/storage.py
moar/thumb.py
moar/thumbnailer.py
moar/utils.py
moar/engines/__init__.py
moar/engines/base.py
moar/engines/wand_engine.py
moar/filters/__init__.py
moar/filters/blur.py
moar/filters/crop.py
moar/filters/rotate.py
tests/__init__.py
tests/conftest.py
tests/test_engines.py
tests/test_filter_crop.py
tests/test_filters.py
tests/test_general.py
tests/test_storage.py
tests/test_thumbnailer.py
tests/utils.py
tests/assets/1_topleft.jpg
tests/assets/2_topright.jpg
tests/assets/3_bottomright.jpg
tests/assets/4_bottomleft.jpg
tests/assets/5_lefttop.jpg
tests/assets/6_righttop.jpg
tests/assets/7_rightbottom.jpg
tests/assets/8_leftbottom.jpg
tests/assets/WandEngine-crop500x500.png
tests/assets/WandEngine-crop50x50-100_20.png
tests/assets/WandEngine-crop50x50-30pc_50pc.png
tests/assets/WandEngine-crop50x50-70.png
tests/assets/WandEngine-crop50x50-center.png
tests/assets/WandEngine-crop50x90.png
tests/assets/WandEngine-filters.png
tests/assets/WandEngine-full.jpeg
tests/assets/WandEngine-rotate60.png
tests/assets/a200x140.jpg
tests/assets/a200x140.png
tests/assets/b94x200.png
tests/assets/t/.gittouch