Metadata-Version: 1.1
Name: Moar
Version: 3.0.0
Summary: Easy thumbnails for everyone
Home-page: http://github.com/lucuma/Moar
Author: Juan-Pablo Scaletti
Author-email: juanpablo@lucumalabs.com
License: MIT license (see LICENSE)
Platform: UNKNOWN
Classifier: Development Status :: 4 - Beta
Classifier: Environment :: Web Environment
Classifier: Intended Audience :: Developers
Classifier: License :: OSI Approved :: MIT License
Classifier: Operating System :: OS Independent
Classifier: Programming Language :: Python
Classifier: Programming Language :: Python :: 2.7
Classifier: Programming Language :: Python :: 3
Classifier: Topic :: Internet :: WWW/HTTP :: Dynamic Content
Classifier: Topic :: Software Development :: Libraries :: Python Modules
